{
    "accessPathLength": 1,
    "useRecursiveAccessPath": true,
    "useThisChainReduction": false,
    "pathAgnosticResults": false,
    "oneResultPerAccessPath": false,
    "mergeNeighbors": false,
    "computeResultPaths": true,
    "enableCallbacks": true,
    "enableCallbackSources": true,
    "stopAfterFirstFlow": false,
    "enableImplicitFlows": true,
    "enableStaticFields": true,
    "enableExceptions": true,
    "enableArraySizeTainting": true,
    "flowSensitiveAliasing": true,
    "enableTypeChecking": true,
    "ignoreFlowsInSystemPackages": false,
    "inspectSources": true,
    "inspectSinks": true,
    "callgraphAlgorithm": "AutomaticSelection",
    "pathBuilder": "ContextInsensitiveSourceFinder",
    "layoutMatchingMode": "MatchSensitiveOnly"
}
